{
  "alfabeto_brasileiro": [
     {
       "nome": "A",
       "imagem": "./assets/images/letras-detalhes/Detalhes-A.png",
       "som_nome": "som_a.mp3",
       "silabas": [],
       "fonemas": [
         {
           "fonema": "a",
           "som_fonema": "som_a_fonema.mp3"
         },
         {
          "fonema": "ã",
          "som_fonema": "som_a_til_fonema.mp3"
         }
       ],
       "possui_quiz": true,
       "possui_palavras": false,
       "possui_silabas": false
     },
     {
       "nome": "B",
       "imagem": "./assets/images/letras-detalhes/Detalhes-B.png",
       "som_nome": "som_b.mp3",
       "silabas": [
         "BA",
         "BE",
         "BI",
         "BO",
         "BU"
       ],
       "palavras": [
         "Banana",
         "Bola",
         "Bolo",
         "Borboleta"
       ],
       "fonemas": [
         {
           "fonema": "b",
           "som_fonema": "som_b_fonema.mp3"
         }
       ],
       "possui_quiz": true,
       "possui_palavras": true,
       "possui_silabas": true
     },
     {
       "nome": "C",
       "imagem": "./assets/images/letras-detalhes/Detalhes-C.png",
       "som_nome": "som_c.mp3",
       "silabas": [
         "CA",
         "CE",
         "CI",
         "CO",
         "CU"
       ],
       "palavras": [
         "Cachorro",
         "Carro",
         "Casa",
         "Coração"
       ],
       "fonemas": [
         {
           "fonema": "c",
           "som_fonema": "som_c_fonema.mp3"
         },
         {
          "fonema": "ç",
          "som_fonema": "som_c_cedilha_fonema.mp3"
         }
       ],
       "possui_quiz": true,
       "possui_palavras": true,
       "possui_silabas": true
     },
     {
       "nome": "D",
       "imagem": "./assets/images/letras-detalhes/Detalhes-D.png",
       "som_nome": "som_d.mp3",
       "silabas": [
         "DA",
         "DE",
         "DI",
         "DO",
         "DU"
       ],
       "palavras": [
         "Dado",
         "Dente",
         "Dinheiro",
         "Dinossauro"
       ],
       "fonemas": [
         {
           "fonema": "d",
           "som_fonema": "som_d_fonema.mp3"
         }
       ],
       "possui_quiz": true,
       "possui_palavras": true,
       "possui_silabas": true
     },
     {
       "nome": "E",
       "imagem": "./assets/images/letras-detalhes/Detalhes-E.png",
       "som_nome": "som_e.mp3",
       "silabas": [],
       "fonemas": [
         {
           "fonema": "e",
           "som_fonema": "som_e.mp3"
         },
         {
          "fonema": "é",
          "som_fonema": "som_e_acento_agudo_fonema.mp3"
         }
       ],
       "possui_quiz": true,
       "possui_palavras": false,
       "possui_silabas": false
     },
     {
       "nome": "F",
       "imagem": "./assets/images/letras-detalhes/Detalhes-F.png",
       "som_nome": "som_f.mp3",
       "silabas": [
         "FA",
         "FE",
         "FI",
         "FO",
         "FU"
       ],
       "palavras": [
         "Fada",
         "Flor",
         "Foguete",
         "Frutas"
       ],
       "fonemas": [
         {
           "fonema": "f",
           "som_fonema": "som_f_fonema.mp3"
         }
       ],
       "possui_quiz": true,
       "possui_palavras": true,
       "possui_silabas": true
     },
     {
       "nome": "G",
       "imagem": "./assets/images/letras-detalhes/Detalhes-G.png",
       "som_nome": "som_g.mp3",
       "silabas": [
         "GA",
         "GE",
         "GI",
         "GO",
         "GU"
       ],
       "palavras": [
         "Gato",
         "Girafa",
         "Golfinho",
         "Guarda chuva"
       ],
       "fonemas": [
         {
           "fonema": "g",
           "som_fonema": "som_j_fonema.mp3"
         },
         {
          "fonema": "gu",
          "som_fonema": "som_gu_fonema.mp3"
         }
       ],
       "possui_quiz": true,
       "possui_palavras": true,
       "possui_silabas": true
     },
     {
       "nome": "H",
       "imagem": "./assets/images/letras-detalhes/Detalhes-H.png",
       "som_nome": "som_h.mp3",
       "silabas": [
         "HA",
         "HE",
         "HI",
         "HO",
         "HU"
       ],
       "palavras": [
         "Hamburguer",
         "Helicóptero",
         "Hipopótamo",
         "Hospital"
       ],
       "fonemas": [],
       "possui_quiz": true,
       "possui_palavras": true,
       "possui_silabas": true
     },
     {
       "nome": "I",
       "imagem": "./assets/images/letras-detalhes/Detalhes-I.png",
       "som_nome": "som_i.mp3",
       "silabas": [],
       "fonemas": [
         {
           "fonema": "i",
           "som_fonema": "som_i_fonema.mp3"
         }
       ],
       "possui_quiz": true,
       "possui_palavras": false,
       "possui_silabas": false
     },
     {
       "nome": "J",
       "imagem": "./assets/images/letras-detalhes/Detalhes-J.png",
       "som_nome": "som_j.mp3",
       "silabas": [
         "JA",
         "JE",
         "JI",
         "JO",
         "JU"
       ],
       "palavras": [
         "Jacaré",
         "Janela",
         "Jarra",
         "Joaninha"
       ],
       "fonemas": [
         {
           "fonema": "j",
           "som_fonema": "som_j_fonema.mp3"
         }
       ],
       "possui_quiz": true,
       "possui_palavras": true,
       "possui_silabas": true
     },
     {
       "nome": "K",
       "imagem": "./assets/images/letras-detalhes/Detalhes-K.png",
       "som_nome": "som_k.mp3",
       "silabas": [
         "KA",
         "KE",
         "KI",
         "KO",
         "KU"
       ],
       "palavras": [
         "Ketchup",
         "Kiwi",
         "Kombi",
         "Kwai"
       ],
       "fonemas": [
         {
           "fonema": "k",
           "som_fonema": "som_k_fonema.mp3"
         }
       ],
       "possui_quiz": true,
       "possui_palavras": true,
       "possui_silabas": true
     },
     {
       "nome": "L",
       "imagem": "./assets/images/letras-detalhes/Detalhes-L.png",
       "som_nome": "som_l.mp3",
       "silabas": [
         "LA",
         "LE",
         "LI",
         "LO",
         "LU"
       ],
       "palavras": [
         "Laranja",
         "Livro",
         "Lua",
         "Lápis"
       ],
       "fonemas": [
         {
           "fonema": "l",
           "som_fonema": "som_l_fonema.mp3"
         }
       ],
       "possui_quiz": true,
       "possui_palavras": true,
       "possui_silabas": true
     },
     {
       "nome": "M",
       "imagem": "./assets/images/letras-detalhes/Detalhes-M.png",
       "som_nome": "som_m.mp3",
       "silabas": [
         "MA",
         "ME",
         "MI",
         "MO",
         "MU"
       ],
       "palavras": [
         "Macaco",
         "Martelo",
         "Mochila",
         "Morango"
       ],
       "fonemas": [
         {
           "fonema": "m",
           "som_fonema": "som_m_fonema.mp3"
         }
       ],
       "possui_quiz": true,
       "possui_palavras": true,
       "possui_silabas": true
     },
     {
       "nome": "N",
       "imagem": "./assets/images/letras-detalhes/Detalhes-N.png",
       "som_nome": "som_n.mp3",
       "silabas": [
         "NA",
         "NE",
         "NI",
         "NO",
         "NU"
       ],
       "palavras": [
         "Nariz",
         "Navio",
         "Ninho",
         "Nuvem"
       ],
       "fonemas": [
         {
           "fonema": "n",
           "som_fonema": "som_n_fonema.mp3"
         }
       ],
       "possui_quiz": true,
       "possui_palavras": true,
       "possui_silabas": true
     },
     {
       "nome": "O",
       "imagem": "./assets/images/letras-detalhes/Detalhes-O.png",
       "som_nome": "som_o.mp3",
       "silabas": [],
       "fonemas": [
         {
           "fonema": "o",
           "som_fonema": "som_o_fonema.mp3"
         },
         {
          "fonema": "ó",
          "som_fonema": "som_o_acento_agudo_fonema.mp3"
         }
       ],
       "possui_quiz": true,
       "possui_palavras": false,
       "possui_silabas": false
     },
     {
       "nome": "P",
       "imagem": "./assets/images/letras-detalhes/Detalhes-P.png",
       "som_nome": "som_p.mp3",
       "silabas": [
         "PA",
         "PE",
         "PI",
         "PO",
         "PU"
       ],
       "palavras": [
         "Pato",
         "Pinguim",
         "Pipoca",
         "Pirulito"
       ],
       "fonemas": [
         {
           "fonema": "p",
           "som_fonema": "som_p_fonema.mp3"
         }
       ],
       "possui_quiz": true,
       "possui_palavras": true,
       "possui_silabas": true
     },
     {
       "nome": "Q",
       "imagem": "./assets/images/letras-detalhes/Detalhes-Q.png",
       "som_nome": "som_q.mp3",
       "silabas": [
         "QA",
         "QE",
         "QI",
         "QO",
         "QU"
       ],
       "palavras": [
         "Quadrado",
         "Quadro",
         "Quatro",
         "Queijo"
       ],
       "fonemas": [
         {
           "fonema": "q",
           "som_fonema": "som_q_fonema.mp3"
         }
       ],
       "possui_quiz": true,
       "possui_palavras": true,
       "possui_silabas": true
     },
     {
       "nome": "R",
       "imagem": "./assets/images/letras-detalhes/Detalhes-R.png",
       "som_nome": "som_r.mp3",
       "silabas": [
         "RA",
         "RE",
         "RI",
         "RO",
         "RU"
       ],
       "palavras": [
         "Raquete",
         "Rato",
         "Relógio",
         "Rinoceronte"
       ],
       "fonemas": [
         {
           "fonema": "r",
           "som_fonema": "som_r_pantera_fonema.mp3"
         },
         {
          "fonema": "rr",
          "som_fonema": "som_r_rato_fonema.mp3"
         }
       ],
       "possui_quiz": true,
       "possui_palavras": true,
       "possui_silabas": true
     },
     {
       "nome": "S",
       "imagem": "./assets/images/letras-detalhes/Detalhes-S.png",
       "som_nome": "som_s.mp3",
       "silabas": [
         "SA",
         "SE",
         "SI",
         "SO",
         "SU"
       ],
       "palavras": [
         "Sapo",
         "Skate",
         "Sol",
         "Sorvete"
       ],
       "fonemas": [
         {
           "fonema": "s",
           "som_fonema": "som_s_fonema.mp3"
         }
       ],
       "possui_quiz": true,
       "possui_palavras": true,
       "possui_silabas": true
     },
     {
       "nome": "T",
       "imagem": "./assets/images/letras-detalhes/Detalhes-T.png",
       "som_nome": "som_t.mp3",
       "silabas": [
         "TA",
         "TE",
         "TI",
         "TO",
         "TU"
       ],
       "palavras": [
         "Tartaruga",
         "Televisão",
         "Tesoura",
         "Tucano"
       ],
       "fonemas": [
         {
           "fonema": "t",
           "som_fonema": "som_t_fonema.mp3"
         }
       ],
       "possui_quiz": true,
       "possui_palavras": true,
       "possui_silabas": true
     },
     {
       "nome": "U",
       "imagem": "./assets/images/letras-detalhes/Detalhes-U.png",
       "som_nome": "som_u.mp3",
       "silabas": [],
       "fonemas": [
         {
           "fonema": "u",
           "som_fonema": "som_u_fonema.mp3"
         }
       ],
       "possui_quiz": true,
       "possui_palavras": false,
       "possui_silabas": false
     },
     {
       "nome": "V",
       "imagem": "./assets/images/letras-detalhes/Detalhes-V.png",
       "som_nome": "som_v.mp3",
       "silabas": [
         "VA",
         "VE",
         "VI",
         "VO",
         "VU"
       ],
       "palavras": [
         "Vaca",
         "Vagalume",
         "Vassoura",
         "Violão"
       ],
       "fonemas": [
         {
           "fonema": "v",
           "som_fonema": "som_v_fonema.mp3"
         }
       ],
       "possui_quiz": true,
       "possui_palavras": true,
       "possui_silabas": true
     },
     {
       "nome": "W",
       "imagem": "./assets/images/letras-detalhes/Detalhes-W.png",
       "som_nome": "som_w.mp3",
       "silabas": [
         "WA",
         "WE",
         "WI",
         "WO",
         "WU"
       ],
       "palavras": [
         "Waffle",
         "Whatsapp",
         "Wifi",
         "Wolverine"
       ],
       "fonemas": [
         {
           "fonema": "v",
           "som_fonema": "som_v_fonema.mp3"
         },
         {
          "fonema": "u",
          "som_fonema": "som_u_fonema.mp3"
         }
       ],
       "possui_quiz": true,
       "possui_palavras": true,
       "possui_silabas": true
     },
     {
       "nome": "X",
       "imagem": "./assets/images/letras-detalhes/Detalhes-X.png",
       "som_nome": "som_x.mp3",
       "silabas": [
         "XA",
         "XE",
         "XI",
         "XO",
         "XU"
       ],
       "palavras": [
         "Xadrez",
         "Xerife",
         "Xilofone",
         "Xícara"
       ],
       "fonemas": [
         {
           "fonema": "x",
           "som_fonema": "som_x_fonema.mp3"
         },
         {
          "fonema": "z",
          "som_fonema": "som_z_fonema.mp3"
         }
       ],
       "possui_quiz": true,
       "possui_palavras": true,
       "possui_silabas": true
     },
     {
       "nome": "Y",
       "imagem": "./assets/images/letras-detalhes/Detalhes-Y.png",
       "som_nome": "som_y.mp3",
       "silabas": [
         "YA",
         "YE",
         "YI",
         "YO",
         "YU"
       ],
       "palavras": [
         "Yakult",
         "Yin yang",
         "Yoda",
         "Youtube"
       ],
       "fonemas": [
         {
           "fonema": "y",
           "som_fonema": "som_i_fonema.mp3"
         }
       ],
       "possui_quiz": true,
       "possui_palavras": true,
       "possui_silabas": true
     },
     {
       "nome": "Z",
       "imagem": "./assets/images/letras-detalhes/Detalhes-Z.png",
       "som_nome": "som_z.mp3",
       "silabas": [
         "ZA",
         "ZE",
         "ZI",
         "ZO",
         "ZU"
       ],
       "palavras": [
         "Zebra",
         "Zoológico",
         "Zumbi",
         "Zíper"
       ],
       "fonemas": [
         {
           "fonema": "z",
           "som_fonema": "som_z_fonema.mp3"
         }
       ],
       "possui_quiz": true,
       "possui_palavras": true,
       "possui_silabas": true
     }
  ]
 }
