{
  "alfabeto_brasileiro": [
    {
      "nome": "A",
      "imagem": "./assets/images/letras-detalhes/Detalhes-A.png",
      "som_nome": "som_a.mp3",
      "fonemas": [
        {
          "fonema": "a",
          "som_fonema": "som_a.mp3"
        },
        {
          "fonema": "ã",
          "som_fonema": "som_a_til.mp3"
        }
      ]
    },
    {
      "nome": "E",
      "imagem": "./assets/images/letras-detalhes/Detalhes-E.png",
      "som_nome": "som_e.mp3",
      "fonemas": [
        {
          "fonema": "e",
          "som_fonema": "som_e.mp3"
        },
        {
          "fonema": "é",
          "som_fonema": "som_e_acento_agudo.mp3"
        }
      ]
    },
    {
      "nome": "I",
      "imagem": "./assets/images/letras-detalhes/Detalhes-I.png",
      "som_nome": "som_i.mp3",
      "fonemas": [
        {
          "fonema": "i",
          "som_fonema": "som_i.mp3"
        }
      ]
    },
    {
      "nome": "O",
      "imagem": "./assets/images/letras-detalhes/Detalhes-O.png",
      "som_nome": "som_o.mp3",
      "fonemas": [
        {
          "fonema": "o",
          "som_fonema": "som_o.mp3"
        },
        {
          "fonema": "ó",
          "som_fonema": "som_o_acento_agudo.mp3"
        }
      ]
    },
    {
      "nome": "U",
      "imagem": "./assets/images/letras-detalhes/Detalhes-U.png",
      "som_nome": "som_u.mp3",
      "fonemas": [
        {
          "fonema": "u",
          "som_fonema": "som_u.mp3"
        }
      ]
    }
  ]
}
